{
  "interactionModel": {
    "languageModel": {
      "invocationName": "viva voce",
      "intents": [
      {
        "name": "AMAZON.NavigateHomeIntent",
        "samples": []
      },
      {
        "name": "AMAZON.HelpIntent",
        "samples": []
      },
      {
        "name": "AMAZON.FallbackIntent",
        "samples": []
      },
      {
        "name": "AMAZON.CancelIntent",
        "samples": []
      },
      {
        "name": "AMAZON.StopIntent",
        "samples": []
      }, 
      {
        "name": "AMAZON.RepeatIntent",
        "samples": []
      }
      ],
      "types": []
    }
  },
  "version": "1"
}